LICENSE
README.md
pyproject.toml
setup.cfg
setup.py
d3cloud/__init__.py
d3cloud/client.py
d3cloud/utils.py
d3cloud.egg-info/PKG-INFO
d3cloud.egg-info/SOURCES.txt
d3cloud.egg-info/dependency_links.txt
d3cloud.egg-info/requires.txt
d3cloud.egg-info/top_level.txt