Metadata-Version: 2.1
Name: d3cloud
Version: 0.12.0
Summary: D3Cloud API
Home-page: https://d3design.tools
Author: Tomas Ruiz
Author-email: tomasruiz@d3atech.com
License: MIT
Project-URL: Bug Tracker, https://github.com/
License-File: LICENSE
